prpy/__init__.py
prpy/constants.py
prpy/helpers.py
prpy/ffmpeg/__init__.py
prpy/ffmpeg/probe.py
prpy/ffmpeg/readwrite.py
prpy/ffmpeg/utils.py
prpy/numpy/__init__.py
prpy/numpy/core.py
prpy/numpy/detect.py
prpy/numpy/face.py
prpy/numpy/filters.py
prpy/numpy/freq.py
prpy/numpy/image.py
prpy/numpy/image_ops.c
prpy/numpy/image_ops.cpython-310-darwin.so
prpy/numpy/interp.py
prpy/numpy/metric.py
prpy/numpy/physio.py
prpy/numpy/rolling.py
prpy/numpy/stride_tricks.py
prpy/numpy/utils.py
prpy/tensorflow/__init__.py
prpy/tensorflow/image.py
prpy/tensorflow/loss.py
prpy/tensorflow/lr_schedule.py
prpy/tensorflow/model_saver.py
prpy/tensorflow/nan.py
prpy/tensorflow/optimizer.py
prpy/tensorflow/signal.py
prpy/torch/__init__.py
prpy/torch/model_saver.py
prpy-0.3.12.dist-info/licenses/LICENSE
prpy-0.3.12.dist-info/METADATA
prpy-0.3.12.dist-info/WHEEL
prpy-0.3.12.dist-info/top_level.txt
prpy-0.3.12.dist-info/RECORD
