Metadata-Version: 2.4
Name: prpy
Version: 0.3.12
Summary: Collection of Python utils for signal, image, and video processing
Author-email: Philipp Rouast <philipp@rouast.com>
License: MIT License
Project-URL: Repository, https://github.com/prouast/prpy.git
Project-URL: Issues, https://github.com/prouast/prpy/issues
Keywords: python,numpy,ffmpeg,tensorflow,torch
Classifier: Programming Language :: Python :: 3
Classifier: Operating System :: OS Independent
Classifier: Development Status :: 4 - Beta
Classifier: License :: OSI Approved :: MIT License
Requires-Python: >=3.9
License-File: LICENSE
Requires-Dist: numpy>=1.24
Provides-Extra: ffmpeg
Requires-Dist: ffmpeg-python; extra == "ffmpeg"
Provides-Extra: numpy
Requires-Dist: scipy; extra == "numpy"
Requires-Dist: Pillow; extra == "numpy"
Requires-Dist: opencv-python; extra == "numpy"
Requires-Dist: psutil; extra == "numpy"
Requires-Dist: scikit-learn; extra == "numpy"
Provides-Extra: numpy-min
Requires-Dist: scipy; extra == "numpy-min"
Requires-Dist: Pillow; extra == "numpy-min"
Requires-Dist: psutil; extra == "numpy-min"
Provides-Extra: tensorflow
Requires-Dist: tensorflow<2.13; extra == "tensorflow"
Provides-Extra: torch
Requires-Dist: torch>=2.1.0; extra == "torch"
Provides-Extra: test
Requires-Dist: pytest; extra == "test"
Requires-Dist: flake8; extra == "test"
Requires-Dist: psutil; extra == "test"
Dynamic: license-file
